[
  {
    "title": "Dornröschenkeller",
    "start": "2026-03-14T14:00:00",
    "end": "2026-03-14T23:00:00",
    "url": "https://www.wienerwein.at/betrieb/4334329/dornroeschenkeller-familie-vrbicky",
    "mapLink": "https://maps.app.goo.gl/hAc5sih71HKBRAQ58",
    "lat": 48.304676,
    "lng": 16.405246
  },
  {
    "title": "Dornröschenkeller",
    "start": "2026-03-15T14:00:00",
    "end": "2026-03-15T23:00:00",
    "url": "https://www.wienerwein.at/betrieb/4334329/dornroeschenkeller-familie-vrbicky",
    "mapLink": "https://maps.app.goo.gl/hAc5sih71HKBRAQ58",
    "lat": 48.304676,
    "lng": 16.405246
  },
  {
    "title": "Dornröschenkeller",
    "start": "2026-03-16T14:00:00",
    "end": "2026-03-16T23:00:00",
    "url": "https://www.wienerwein.at/betrieb/4334329/dornroeschenkeller-familie-vrbicky",
    "mapLink": "https://maps.app.goo.gl/hAc5sih71HKBRAQ58",
    "lat": 48.304676,
    "lng": 16.405246
  },
  {
    "title": "Dornröschenkeller",
    "start": "2026-03-17T14:00:00",
    "end": "2026-03-17T23:00:00",
    "url": "https://www.wienerwein.at/betrieb/4334329/dornroeschenkeller-familie-vrbicky",
    "mapLink": "https://maps.app.goo.gl/hAc5sih71HKBRAQ58",
    "lat": 48.304676,
    "lng": 16.405246
  },
  {
    "title": "Dornröschenkeller",
    "start": "2026-03-18T14:00:00",
    "end": "2026-03-18T23:00:00",
    "url": "https://www.wienerwein.at/betrieb/4334329/dornroeschenkeller-familie-vrbicky",
    "mapLink": "https://maps.app.goo.gl/hAc5sih71HKBRAQ58",
    "lat": 48.304676,
    "lng": 16.405246
  },
  {
    "title": "Dornröschenkeller",
    "start": "2026-03-19T14:00:00",
    "end": "2026-03-19T23:00:00",
    "url": "https://www.wienerwein.at/betrieb/4334329/dornroeschenkeller-familie-vrbicky",
    "mapLink": "https://maps.app.goo.gl/hAc5sih71HKBRAQ58",
    "lat": 48.304676,
    "lng": 16.405246
  },
  {
    "title": "Dornröschenkeller",
    "start": "2026-03-20T14:00:00",
    "end": "2026-03-20T23:00:00",
    "url": "https://www.wienerwein.at/betrieb/4334329/dornroeschenkeller-familie-vrbicky",
    "mapLink": "https://maps.app.goo.gl/hAc5sih71HKBRAQ58",
    "lat": 48.304676,
    "lng": 16.405246
  },
  {
    "title": "Dornröschenkeller",
    "start": "2026-03-21T14:00:00",
    "end": "2026-03-21T23:00:00",
    "url": "https://www.wienerwein.at/betrieb/4334329/dornroeschenkeller-familie-vrbicky",
    "mapLink": "https://maps.app.goo.gl/hAc5sih71HKBRAQ58",
    "lat": 48.304676,
    "lng": 16.405246
  },
  {
    "title": "Dornröschenkeller",
    "start": "2026-03-22T14:00:00",
    "end": "2026-03-22T23:00:00",
    "url": "https://www.wienerwein.at/betrieb/4334329/dornroeschenkeller-familie-vrbicky",
    "mapLink": "https://maps.app.goo.gl/hAc5sih71HKBRAQ58",
    "lat": 48.304676,
    "lng": 16.405246
  },
  {
    "title": "Dornröschenkeller",
    "start": "2026-03-23T14:00:00",
    "end": "2026-03-23T23:00:00",
    "url": "https://www.wienerwein.at/betrieb/4334329/dornroeschenkeller-familie-vrbicky",
    "mapLink": "https://maps.app.goo.gl/hAc5sih71HKBRAQ58",
    "lat": 48.304676,
    "lng": 16.405246
  },
  {
    "title": "Dornröschenkeller",
    "start": "2026-03-24T14:00:00",
    "end": "2026-03-24T23:00:00",
    "url": "https://www.wienerwein.at/betrieb/4334329/dornroeschenkeller-familie-vrbicky",
    "mapLink": "https://maps.app.goo.gl/hAc5sih71HKBRAQ58",
    "lat": 48.304676,
    "lng": 16.405246
  },
  {
    "title": "Dornröschenkeller",
    "start": "2026-03-25T14:00:00",
    "end": "2026-03-25T23:00:00",
    "url": "https://www.wienerwein.at/betrieb/4334329/dornroeschenkeller-familie-vrbicky",
    "mapLink": "https://maps.app.goo.gl/hAc5sih71HKBRAQ58",
    "lat": 48.304676,
    "lng": 16.405246
  },
  {
    "title": "Dornröschenkeller",
    "start": "2026-03-26T14:00:00",
    "end": "2026-03-26T23:00:00",
    "url": "https://www.wienerwein.at/betrieb/4334329/dornroeschenkeller-familie-vrbicky",
    "mapLink": "https://maps.app.goo.gl/hAc5sih71HKBRAQ58",
    "lat": 48.304676,
    "lng": 16.405246
  },
  {
    "title": "Dornröschenkeller",
    "start": "2026-03-27T14:00:00",
    "end": "2026-03-27T23:00:00",
    "url": "https://www.wienerwein.at/betrieb/4334329/dornroeschenkeller-familie-vrbicky",
    "mapLink": "https://maps.app.goo.gl/hAc5sih71HKBRAQ58",
    "lat": 48.304676,
    "lng": 16.405246
  },
  {
    "title": "Dornröschenkeller",
    "start": "2026-03-28T14:00:00",
    "end": "2026-03-28T23:00:00",
    "url": "https://www.wienerwein.at/betrieb/4334329/dornroeschenkeller-familie-vrbicky",
    "mapLink": "https://maps.app.goo.gl/hAc5sih71HKBRAQ58",
    "lat": 48.304676,
    "lng": 16.405246
  },
  {
    "title": "Dornröschenkeller",
    "start": "2026-03-29T14:00:00",
    "end": "2026-03-29T23:00:00",
    "url": "https://www.wienerwein.at/betrieb/4334329/dornroeschenkeller-familie-vrbicky",
    "mapLink": "https://maps.app.goo.gl/hAc5sih71HKBRAQ58",
    "lat": 48.304676,
    "lng": 16.405246
  },
  {
    "title": "Dornröschenkeller",
    "start": "2026-04-11T14:00:00",
    "end": "2026-04-11T23:00:00",
    "url": "https://www.wienerwein.at/betrieb/4334329/dornroeschenkeller-familie-vrbicky",
    "mapLink": "https://maps.app.goo.gl/hAc5sih71HKBRAQ58",
    "lat": 48.304676,
    "lng": 16.405246
  },
  {
    "title": "Dornröschenkeller",
    "start": "2026-04-12T14:00:00",
    "end": "2026-04-12T23:00:00",
    "url": "https://www.wienerwein.at/betrieb/4334329/dornroeschenkeller-familie-vrbicky",
    "mapLink": "https://maps.app.goo.gl/hAc5sih71HKBRAQ58",
    "lat": 48.304676,
    "lng": 16.405246
  },
  {
    "title": "Dornröschenkeller",
    "start": "2026-04-13T14:00:00",
    "end": "2026-04-13T23:00:00",
    "url": "https://www.wienerwein.at/betrieb/4334329/dornroeschenkeller-familie-vrbicky",
    "mapLink": "https://maps.app.goo.gl/hAc5sih71HKBRAQ58",
    "lat": 48.304676,
    "lng": 16.405246
  },
  {
    "title": "Dornröschenkeller",
    "start": "2026-04-14T14:00:00",
    "end": "2026-04-14T23:00:00",
    "url": "https://www.wienerwein.at/betrieb/4334329/dornroeschenkeller-familie-vrbicky",
    "mapLink": "https://maps.app.goo.gl/hAc5sih71HKBRAQ58",
    "lat": 48.304676,
    "lng": 16.405246
  },
  {
    "title": "Dornröschenkeller",
    "start": "2026-04-15T14:00:00",
    "end": "2026-04-15T23:00:00",
    "url": "https://www.wienerwein.at/betrieb/4334329/dornroeschenkeller-familie-vrbicky",
    "mapLink": "https://maps.app.goo.gl/hAc5sih71HKBRAQ58",
    "lat": 48.304676,
    "lng": 16.405246
  },
  {
    "title": "Dornröschenkeller",
    "start": "2026-04-16T14:00:00",
    "end": "2026-04-16T23:00:00",
    "url": "https://www.wienerwein.at/betrieb/4334329/dornroeschenkeller-familie-vrbicky",
    "mapLink": "https://maps.app.goo.gl/hAc5sih71HKBRAQ58",
    "lat": 48.304676,
    "lng": 16.405246
  },
  {
    "title": "Dornröschenkeller",
    "start": "2026-04-17T14:00:00",
    "end": "2026-04-17T23:00:00",
    "url": "https://www.wienerwein.at/betrieb/4334329/dornroeschenkeller-familie-vrbicky",
    "mapLink": "https://maps.app.goo.gl/hAc5sih71HKBRAQ58",
    "lat": 48.304676,
    "lng": 16.405246
  },
  {
    "title": "Dornröschenkeller",
    "start": "2026-04-18T14:00:00",
    "end": "2026-04-18T23:00:00",
    "url": "https://www.wienerwein.at/betrieb/4334329/dornroeschenkeller-familie-vrbicky",
    "mapLink": "https://maps.app.goo.gl/hAc5sih71HKBRAQ58",
    "lat": 48.304676,
    "lng": 16.405246
  },
  {
    "title": "Dornröschenkeller",
    "start": "2026-04-19T14:00:00",
    "end": "2026-04-19T23:00:00",
    "url": "https://www.wienerwein.at/betrieb/4334329/dornroeschenkeller-familie-vrbicky",
    "mapLink": "https://maps.app.goo.gl/hAc5sih71HKBRAQ58",
    "lat": 48.304676,
    "lng": 16.405246
  },
  {
    "title": "Dornröschenkeller",
    "start": "2026-04-20T14:00:00",
    "end": "2026-04-20T23:00:00",
    "url": "https://www.wienerwein.at/betrieb/4334329/dornroeschenkeller-familie-vrbicky",
    "mapLink": "https://maps.app.goo.gl/hAc5sih71HKBRAQ58",
    "lat": 48.304676,
    "lng": 16.405246
  },
  {
    "title": "Dornröschenkeller",
    "start": "2026-04-21T14:00:00",
    "end": "2026-04-21T23:00:00",
    "url": "https://www.wienerwein.at/betrieb/4334329/dornroeschenkeller-familie-vrbicky",
    "mapLink": "https://maps.app.goo.gl/hAc5sih71HKBRAQ58",
    "lat": 48.304676,
    "lng": 16.405246
  },
  {
    "title": "Dornröschenkeller",
    "start": "2026-04-22T14:00:00",
    "end": "2026-04-22T23:00:00",
    "url": "https://www.wienerwein.at/betrieb/4334329/dornroeschenkeller-familie-vrbicky",
    "mapLink": "https://maps.app.goo.gl/hAc5sih71HKBRAQ58",
    "lat": 48.304676,
    "lng": 16.405246
  },
  {
    "title": "Dornröschenkeller",
    "start": "2026-04-23T14:00:00",
    "end": "2026-04-23T23:00:00",
    "url": "https://www.wienerwein.at/betrieb/4334329/dornroeschenkeller-familie-vrbicky",
    "mapLink": "https://maps.app.goo.gl/hAc5sih71HKBRAQ58",
    "lat": 48.304676,
    "lng": 16.405246
  },
  {
    "title": "Dornröschenkeller",
    "start": "2026-04-24T14:00:00",
    "end": "2026-04-24T23:00:00",
    "url": "https://www.wienerwein.at/betrieb/4334329/dornroeschenkeller-familie-vrbicky",
    "mapLink": "https://maps.app.goo.gl/hAc5sih71HKBRAQ58",
    "lat": 48.304676,
    "lng": 16.405246
  },
  {
    "title": "Dornröschenkeller",
    "start": "2026-04-25T14:00:00",
    "end": "2026-04-25T23:00:00",
    "url": "https://www.wienerwein.at/betrieb/4334329/dornroeschenkeller-familie-vrbicky",
    "mapLink": "https://maps.app.goo.gl/hAc5sih71HKBRAQ58",
    "lat": 48.304676,
    "lng": 16.405246
  },
  {
    "title": "Dornröschenkeller",
    "start": "2026-04-26T14:00:00",
    "end": "2026-04-26T23:00:00",
    "url": "https://www.wienerwein.at/betrieb/4334329/dornroeschenkeller-familie-vrbicky",
    "mapLink": "https://maps.app.goo.gl/hAc5sih71HKBRAQ58",
    "lat": 48.304676,
    "lng": 16.405246
  },
  {
    "title": "Dornröschenkeller",
    "start": "2026-05-09T14:00:00",
    "end": "2026-05-09T23:00:00",
    "url": "https://www.wienerwein.at/betrieb/4334329/dornroeschenkeller-familie-vrbicky",
    "mapLink": "https://maps.app.goo.gl/hAc5sih71HKBRAQ58",
    "lat": 48.304676,
    "lng": 16.405246
  },
  {
    "title": "Dornröschenkeller",
    "start": "2026-05-10T14:00:00",
    "end": "2026-05-10T23:00:00",
    "url": "https://www.wienerwein.at/betrieb/4334329/dornroeschenkeller-familie-vrbicky",
    "mapLink": "https://maps.app.goo.gl/hAc5sih71HKBRAQ58",
    "lat": 48.304676,
    "lng": 16.405246
  },
  {
    "title": "Dornröschenkeller",
    "start": "2026-05-11T14:00:00",
    "end": "2026-05-11T23:00:00",
    "url": "https://www.wienerwein.at/betrieb/4334329/dornroeschenkeller-familie-vrbicky",
    "mapLink": "https://maps.app.goo.gl/hAc5sih71HKBRAQ58",
    "lat": 48.304676,
    "lng": 16.405246
  },
  {
    "title": "Dornröschenkeller",
    "start": "2026-05-12T14:00:00",
    "end": "2026-05-12T23:00:00",
    "url": "https://www.wienerwein.at/betrieb/4334329/dornroeschenkeller-familie-vrbicky",
    "mapLink": "https://maps.app.goo.gl/hAc5sih71HKBRAQ58",
    "lat": 48.304676,
    "lng": 16.405246
  },
  {
    "title": "Dornröschenkeller",
    "start": "2026-05-13T14:00:00",
    "end": "2026-05-13T23:00:00",
    "url": "https://www.wienerwein.at/betrieb/4334329/dornroeschenkeller-familie-vrbicky",
    "mapLink": "https://maps.app.goo.gl/hAc5sih71HKBRAQ58",
    "lat": 48.304676,
    "lng": 16.405246
  },
  {
    "title": "Dornröschenkeller",
    "start": "2026-05-14T14:00:00",
    "end": "2026-05-14T23:00:00",
    "url": "https://www.wienerwein.at/betrieb/4334329/dornroeschenkeller-familie-vrbicky",
    "mapLink": "https://maps.app.goo.gl/hAc5sih71HKBRAQ58",
    "lat": 48.304676,
    "lng": 16.405246
  },
  {
    "title": "Dornröschenkeller",
    "start": "2026-05-15T14:00:00",
    "end": "2026-05-15T23:00:00",
    "url": "https://www.wienerwein.at/betrieb/4334329/dornroeschenkeller-familie-vrbicky",
    "mapLink": "https://maps.app.goo.gl/hAc5sih71HKBRAQ58",
    "lat": 48.304676,
    "lng": 16.405246
  },
  {
    "title": "Dornröschenkeller",
    "start": "2026-05-16T14:00:00",
    "end": "2026-05-16T23:00:00",
    "url": "https://www.wienerwein.at/betrieb/4334329/dornroeschenkeller-familie-vrbicky",
    "mapLink": "https://maps.app.goo.gl/hAc5sih71HKBRAQ58",
    "lat": 48.304676,
    "lng": 16.405246
  },
  {
    "title": "Dornröschenkeller",
    "start": "2026-05-17T14:00:00",
    "end": "2026-05-17T23:00:00",
    "url": "https://www.wienerwein.at/betrieb/4334329/dornroeschenkeller-familie-vrbicky",
    "mapLink": "https://maps.app.goo.gl/hAc5sih71HKBRAQ58",
    "lat": 48.304676,
    "lng": 16.405246
  },
  {
    "title": "Dornröschenkeller",
    "start": "2026-05-18T14:00:00",
    "end": "2026-05-18T23:00:00",
    "url": "https://www.wienerwein.at/betrieb/4334329/dornroeschenkeller-familie-vrbicky",
    "mapLink": "https://maps.app.goo.gl/hAc5sih71HKBRAQ58",
    "lat": 48.304676,
    "lng": 16.405246
  },
  {
    "title": "Dornröschenkeller",
    "start": "2026-05-19T14:00:00",
    "end": "2026-05-19T23:00:00",
    "url": "https://www.wienerwein.at/betrieb/4334329/dornroeschenkeller-familie-vrbicky",
    "mapLink": "https://maps.app.goo.gl/hAc5sih71HKBRAQ58",
    "lat": 48.304676,
    "lng": 16.405246
  },
  {
    "title": "Dornröschenkeller",
    "start": "2026-05-20T14:00:00",
    "end": "2026-05-20T23:00:00",
    "url": "https://www.wienerwein.at/betrieb/4334329/dornroeschenkeller-familie-vrbicky",
    "mapLink": "https://maps.app.goo.gl/hAc5sih71HKBRAQ58",
    "lat": 48.304676,
    "lng": 16.405246
  },
  {
    "title": "Dornröschenkeller",
    "start": "2026-05-21T14:00:00",
    "end": "2026-05-21T23:00:00",
    "url": "https://www.wienerwein.at/betrieb/4334329/dornroeschenkeller-familie-vrbicky",
    "mapLink": "https://maps.app.goo.gl/hAc5sih71HKBRAQ58",
    "lat": 48.304676,
    "lng": 16.405246
  },
  {
    "title": "Dornröschenkeller",
    "start": "2026-05-22T14:00:00",
    "end": "2026-05-22T23:00:00",
    "url": "https://www.wienerwein.at/betrieb/4334329/dornroeschenkeller-familie-vrbicky",
    "mapLink": "https://maps.app.goo.gl/hAc5sih71HKBRAQ58",
    "lat": 48.304676,
    "lng": 16.405246
  },
  {
    "title": "Dornröschenkeller",
    "start": "2026-05-23T14:00:00",
    "end": "2026-05-23T23:00:00",
    "url": "https://www.wienerwein.at/betrieb/4334329/dornroeschenkeller-familie-vrbicky",
    "mapLink": "https://maps.app.goo.gl/hAc5sih71HKBRAQ58",
    "lat": 48.304676,
    "lng": 16.405246
  },
  {
    "title": "Dornröschenkeller",
    "start": "2026-05-24T14:00:00",
    "end": "2026-05-24T23:00:00",
    "url": "https://www.wienerwein.at/betrieb/4334329/dornroeschenkeller-familie-vrbicky",
    "mapLink": "https://maps.app.goo.gl/hAc5sih71HKBRAQ58",
    "lat": 48.304676,
    "lng": 16.405246
  }
]
